{
	"#comment": "LOD 253",
	"objects": [ {
			"objclass": "LevelDefinition",
			"objdata": {
				"Description": "[PREMIUM_PLANT_QUEST_LOD_DESC]",
				"DraperPromo": "murkadamia",
				"ForceToWorldMap": true,
				"Loot": "RTID(DefaultLoot@LevelModules)",
				"Modules": [ "RTID(StandardIntro@LevelModules)", "RTID(LevelEscalationModule@CurrentLevel)", "RTID(FrontLawnMowers@LevelModules)", "RTID(NewWaves@CurrentLevel)", "RTID(DefaultZombieWinCondition@LevelModules)", "RTID(Gravestones@CurrentLevel)", "RTID(SeedBank@CurrentLevel)", "RTID(ZombiesDeadWinCon@LevelModules)", "RTID(DefaultSunDropper@LevelModules)", "RTID(ProtectThePlant@CurrentLevel)" ],
				"Name": "[PREMIUM_PLANT_QUEST_LOD_NAME]",
				"NormalPresentTable": "egypt_normal_01",
				"RepeatPlayForceToWorldMap": true,
				"ShinyPresentTable": "egypt_shiny_01",
				"StageModule": "RTID(FrontLawnStage@LevelModules)"
			}
		}, {
			"aliases": [ "ProtectThePlant" ],
			"objclass": "ProtectThePlantChallengeProperties",
			"objdata": {
				"MustProtectCount": 5,
				"Plants": [ {
						"GridX": 2,
						"GridY": 0,
						"PlantType": "moonflower"
					}, {
						"GridX": 3,
						"GridY": 1,
						"PlantType": "moonflower"
					}, {
						"GridX": 4,
						"GridY": 2,
						"PlantType": "moonflower"
					}, {
						"GridX": 3,
						"GridY": 3,
						"PlantType": "moonflower"
					}, {
						"GridX": 2,
						"GridY": 4,
						"PlantType": "moonflower"
					} ]
			}
		}, {
			"aliases": [ "ChallengeModule" ],
			"objclass": "StarChallengeModuleProperties",
			"objdata": {
				"Challenges": [ [ "RTID(BeatTheLevel@CurrentLevel)" ] ],
				"ChallengesAlwaysAvailable": true
			}
		}, {
			"aliases": [ "BeatTheLevel" ],
			"objclass": "StarChallengeBeatTheLevelProps",
			"objdata": {
				"Description": "[STARCHALLENGE_PROTECT_THE_PLANT]",
				"DescriptiveName": "[STARCHALLENGE_PROTECT_THE_PLANT_NAME]"
			}
		}, {
			"aliases": [ "SeedBank" ],
			"objclass": "SeedBankProperties",
			"objdata": {
				"PresetPlantList": [ {
						"Level": -1,
						"PlantType": "moonflower"
					}, {
						"Level": -1,
						"PlantType": "murkadamia"
					}, {
						"Level": -1,
						"PlantType": "dusklobber"
					}, {
						"Level": -1,
						"PlantType": "goldbloom"
					}, {
						"Level": -1,
						"PlantType": "iceburg"
					}, {
						"Level": -1,
						"PlantType": "imitater"
					} ],
				"SelectionMethod": "preset"
			}
		}, {
			"aliases": [ "LevelEscalationModule" ],
			"objclass": "LevelEscalationModuleProperties",
			"objdata": {
				"FlagCount": 5,
				"PlantfoodToSpawnCount": 4,
				"PointIncrementPerWave": 100,
				"StartingPoints": 50,
				"WaveManagerProps": "RTID(WaveManagerProps@CurrentLevel)",
				"WavesPerFlag": 3,
				"ZombiePool": [ "RTID(eighties@ZombieTypes)", "RTID(eighties_armor1@ZombieTypes)", "RTID(modern_newspaper@ZombieTypes)" ]
			}
		}, {
			"aliases": [ "WaveManagerProps" ],
			"objclass": "WaveManagerProperties",
			"objdata": {
				"FlagWaveInterval": 3,
				"LevelJam": "pop",
				"MaxNextWaveHealthPercentage": 0.9,
				"MinNextWaveHealthPercentage": 0.8,
				"WaveCount": 15,
				"WaveSpendingPointIncrement": 100,
				"WaveSpendingPoints": 100,
				"Waves": [ [ "RTID(Wave1@CurrentLevel)" ], [ "RTID(Wave2@CurrentLevel)" ], [ "RTID(Wave3@CurrentLevel)" ], [ "RTID(Wave4@CurrentLevel)" ], [ "RTID(Wave5@CurrentLevel)" ], [ "RTID(Wave6@CurrentLevel)" ], [ "RTID(Wave7@CurrentLevel)" ], [ "RTID(Wave8@CurrentLevel)" ], [ "RTID(Wave9@CurrentLevel)" ], [ "RTID(Wave10@CurrentLevel)" ], [ "RTID(Wave11@CurrentLevel)" ], [ "RTID(Wave12@CurrentLevel)" ], [ "RTID(Wave13@CurrentLevel)" ], [ "RTID(Wave14@CurrentLevel)" ], [ "RTID(Wave15@CurrentLevel)" ] ]
			}
		}, {
			"aliases": [ "Wave1" ],
			"objclass": "SpawnZombiesJitteredWaveActionProps",
			"objdata": {
				"Zombies": [ {
						"Type": "RTID(explorer@ZombieTypes)"
					}, {
						"Type": "RTID(camel_manyhump@ZombieTypes)"
					} ]
			}
		}, {
			"aliases": [ "Wave2" ],
			"objclass": "SpawnZombiesJitteredWaveActionProps",
			"objdata": {
				"Zombies": [ {
						"Type": "RTID(camel_manyhump@ZombieTypes)"
					}, {
						"Type": "RTID(explorer@ZombieTypes)"
					} ]
			}
		}, {
			"aliases": [ "Wave3" ],
			"objclass": "SpawnZombiesJitteredWaveActionProps",
			"objdata": {
				"Zombies": [ {
						"Type": "RTID(camel_manyhump@ZombieTypes)"
					}, {
						"Type": "RTID(explorer@ZombieTypes)"
					}, {
						"Type": "RTID(roman_shield_triad@ZombieTypes)"
					} ]
			}
		}, {
			"aliases": [ "Wave4" ],
			"objclass": "SpawnZombiesJitteredWaveActionProps",
			"objdata": {
				"Zombies": [ {
						"Type": "RTID(camel_manyhump@ZombieTypes)"
					}, {
						"Type": "RTID(explorer@ZombieTypes)"
					} ]
			}
		}, {
			"aliases": [ "Wave5" ],
			"objclass": "SpawnZombiesJitteredWaveActionProps",
			"objdata": {
				"Zombies": [ {
						"Type": "RTID(roman_shield_triad@ZombieTypes)"
					}, {
						"Type": "RTID(explorer@ZombieTypes)"
					} ]
			}
		}, {
			"aliases": [ "Wave6" ],
			"objclass": "SpawnZombiesJitteredWaveActionProps",
			"objdata": {
				"Zombies": [ {
						"Type": "RTID(roman_shield_triad@ZombieTypes)"
					}, {
						"Type": "RTID(explorer@ZombieTypes)"
					}, {
						"Type": "RTID(camel_manyhump@ZombieTypes)"
					}, {
						"Type": "RTID(explorer@ZombieTypes)"
					}, {
						"Type": "RTID(roman_shield_triad@ZombieTypes)"
					}, {
						"Type": "RTID(camel_manyhump@ZombieTypes)"
					} ]
			}
		}, {
			"aliases": [ "Wave7" ],
			"objclass": "SpawnZombiesJitteredWaveActionProps",
			"objdata": {
				"Zombies": [ {
						"Type": "RTID(explorer@ZombieTypes)"
					}, {
						"Type": "RTID(eighties_glitter@ZombieTypes)"
					}, {
						"Type": "RTID(roman_shield_triad@ZombieTypes)"
					} ]
			}
		}, {
			"aliases": [ "Wave8" ],
			"objclass": "SpawnZombiesJitteredWaveActionProps",
			"objdata": {
				"Zombies": [ {
						"Type": "RTID(eighties_glitter@ZombieTypes)"
					}, {
						"Type": "RTID(roman_shield_triad@ZombieTypes)"
					}, {
						"Type": "RTID(explorer@ZombieTypes)"
					} ]
			}
		}, {
			"aliases": [ "Wave9" ],
			"objclass": "SpawnZombiesJitteredWaveActionProps",
			"objdata": {
				"Zombies": [ {
						"Type": "RTID(explorer@ZombieTypes)"
					}, {
						"Type": "RTID(roman_shield_triad@ZombieTypes)"
					}, {
						"Type": "RTID(camel_manyhump@ZombieTypes)"
					}, {
						"Type": "RTID(roman_shield_triad@ZombieTypes)"
					}, {
						"Type": "RTID(explorer@ZombieTypes)"
					}, {
						"Type": "RTID(camel_manyhump@ZombieTypes)"
					}, {
						"Type": "RTID(explorer@ZombieTypes)"
					} ]
			}
		}, {
			"aliases": [ "Wave10" ],
			"objclass": "SpawnZombiesJitteredWaveActionProps",
			"objdata": {
				"Zombies": [ {
						"Type": "RTID(eighties_glitter@ZombieTypes)"
					}, {
						"Type": "RTID(roman_medusa@ZombieTypes)"
					} ]
			}
		}, {
			"aliases": [ "Wave11" ],
			"objclass": "SpawnZombiesJitteredWaveActionProps",
			"objdata": {
				"Zombies": [ {
						"Type": "RTID(eighties_glitter@ZombieTypes)"
					}, {
						"Type": "RTID(roman_medusa@ZombieTypes)"
					} ]
			}
		}, {
			"aliases": [ "Wave12" ],
			"objclass": "SpawnZombiesJitteredWaveActionProps",
			"objdata": {
				"Zombies": [ {
						"Type": "RTID(eighties_glitter@ZombieTypes)"
					}, {
						"Type": "RTID(roman_shield_triad@ZombieTypes)"
					}, {
						"Type": "RTID(roman_medusa@ZombieTypes)"
					}, {
						"Type": "RTID(roman_shield_triad@ZombieTypes)"
					}, {
						"Type": "RTID(explorer@ZombieTypes)"
					}, {
						"Type": "RTID(roman_medusa@ZombieTypes)"
					} ]
			}
		}, {
			"aliases": [ "Gravestones" ],
			"objclass": "GravestoneProperties",
			"objdata": {}
		}, {
			"aliases": [ "NewWaves" ],
			"objclass": "WaveManagerModuleProperties",
			"objdata": {}
		}, {
			"aliases": [ "Wave13" ],
			"objclass": "SpawnZombiesJitteredWaveActionProps",
			"objdata": {
				"Zombies": [ {
						"Type": "RTID(eighties_glitter@ZombieTypes)"
					}, {
						"Type": "RTID(roman_shield_triad@ZombieTypes)"
					}, {
						"Type": "RTID(newspaper_veteran@ZombieTypes)"
					}, {
						"Type": "RTID(explorer@ZombieTypes)"
					} ]
			}
		}, {
			"aliases": [ "Wave14" ],
			"objclass": "SpawnZombiesJitteredWaveActionProps",
			"objdata": {
				"Zombies": [ {
						"Type": "RTID(roman_shield_triad@ZombieTypes)"
					}, {
						"Type": "RTID(newspaper_veteran@ZombieTypes)"
					}, {
						"Type": "RTID(explorer@ZombieTypes)"
					}, {
						"Type": "RTID(roman_medusa@ZombieTypes)"
					} ]
			}
		}, {
			"aliases": [ "Wave15" ],
			"objclass": "SpawnZombiesJitteredWaveActionProps",
			"objdata": {
				"Zombies": [ {
						"Type": "RTID(eighties_glitter@ZombieTypes)"
					}, {
						"Type": "RTID(roman_shield_triad@ZombieTypes)"
					}, {
						"Type": "RTID(newspaper_veteran@ZombieTypes)"
					}, {
						"Type": "RTID(newspaper_veteran@ZombieTypes)"
					}, {
						"Type": "RTID(newspaper_veteran@ZombieTypes)"
					}, {
						"Type": "RTID(roman_medusa@ZombieTypes)"
					}, {
						"Type": "RTID(roman_medusa@ZombieTypes)"
					}, {
						"Type": "RTID(roman_medusa@ZombieTypes)"
					} ]
			}
		} ],
	"version": 1
}