{
	"#comment": "LoD imitater + iceburg",
	"objects": [ {
			"objclass": "LevelDefinition",
			"objdata": {
				"Description": "[PREMIUM_PLANT_QUEST_LOD_DESC]",
				"DraperPromo": "imitater",
				"ForceToWorldMap": true,
				"Loot": "RTID(DefaultLoot@LevelModules)",
				"Modules": [ "RTID(StandardIntro@LevelModules)", "RTID(LevelEscalationModule@CurrentLevel)", "RTID(FrontLawnMowers@LevelModules)", "RTID(DefaultSunDropper@LevelModules)", "RTID(NewWaves@CurrentLevel)", "RTID(SeedBank@CurrentLevel)", "RTID(DefaultZombieWinCondition@LevelModules)", "RTID(Gravestones@CurrentLevel)", "RTID(ZombiesDeadWinCon@LevelModules)" ],
				"Name": "[PREMIUM_PLANT_QUEST_LOD_NAME]",
				"NormalPresentTable": "egypt_normal_01",
				"RepeatPlayForceToWorldMap": true,
				"ShinyPresentTable": "egypt_shiny_01",
				"StageModule": "RTID(FrontLawnStage@LevelModules)"
			}
		}, {
			"aliases": [ "SeedBank" ],
			"objclass": "SeedBankProperties",
			"objdata": {
				"PresetPlantList": [ {
						"Level": -1,
						"PlantType": "primalsunflower"
					}, {
						"Level": -1,
						"PlantType": "tallnut"
					}, {
						"Level": -1,
						"PlantType": "imitater"
					}, {
						"Level": -1,
						"PlantType": "electricblueberry"
					}, {
						"Level": -1,
						"PlantType": "imitater"
					} ],
				"SelectionMethod": "preset"
			}
		}, {
			"aliases": [ "WaveManagerProps" ],
			"objclass": "WaveManagerProperties",
			"objdata": {
				"FlagWaveInterval": 6,
				"MaxNextWaveHealthPercentage": 0.9,
				"MinNextWaveHealthPercentage": 0.8,
				"WaveCount": 12,
				"Waves": [ [ "RTID(Wave1@CurrentLevel)" ], [ "RTID(Wave2@CurrentLevel)" ], [ "RTID(Wave3@CurrentLevel)" ], [ "RTID(Wave4@CurrentLevel)" ], [ "RTID(Wave5@CurrentLevel)" ], [ "RTID(Wave6@CurrentLevel)" ], [ "RTID(Wave7@CurrentLevel)" ], [ "RTID(Wave8@CurrentLevel)" ], [ "RTID(Wave9@CurrentLevel)" ], [ "RTID(Wave10@CurrentLevel)" ], [ "RTID(Wave11@CurrentLevel)" ], [ "RTID(Wave12@CurrentLevel)", "RTID(Wave12StormEvent0@CurrentLevel)" ] ]
			}
		}, {
			"aliases": [ "Wave1" ],
			"objclass": "SpawnZombiesJitteredWaveActionProps",
			"objdata": {
				"Zombies": [ {
						"Type": "RTID(lostcity_jane@ZombieTypes)"
					} ]
			}
		}, {
			"aliases": [ "Wave2" ],
			"objclass": "SpawnZombiesJitteredWaveActionProps",
			"objdata": {
				"Zombies": [ {
						"Type": "RTID(lostcity_jane@ZombieTypes)"
					} ]
			}
		}, {
			"aliases": [ "Wave3" ],
			"objclass": "SpawnZombiesJitteredWaveActionProps",
			"objdata": {
				"Zombies": [ {
						"Type": "RTID(lostcity_jane@ZombieTypes)"
					}, {
						"Type": "RTID(lostcity_jane@ZombieTypes)"
					} ]
			}
		}, {
			"aliases": [ "Wave4" ],
			"objclass": "SpawnZombiesJitteredWaveActionProps",
			"objdata": {
				"AdditionalPlantfood": 1,
				"Zombies": [ {
						"Row": "1",
						"Type": "RTID(seagull@ZombieTypes)"
					} ]
			}
		}, {
			"aliases": [ "Wave5" ],
			"objclass": "SpawnZombiesJitteredWaveActionProps",
			"objdata": {
				"AdditionalPlantfood": 1,
				"Zombies": [ {
						"Row": "1",
						"Type": "RTID(seagull@ZombieTypes)"
					}, {
						"Type": "RTID(seagull@ZombieTypes)"
					} ]
			}
		}, {
			"aliases": [ "Wave6" ],
			"objclass": "SpawnZombiesJitteredWaveActionProps",
			"objdata": {
				"AdditionalPlantfood": 1,
				"Zombies": [ {
						"Row": "2",
						"Type": "RTID(lostcity_jane@ZombieTypes)"
					}, {
						"Type": "RTID(seagull@ZombieTypes)"
					} ]
			}
		}, {
			"aliases": [ "Wave7" ],
			"objclass": "SpawnZombiesJitteredWaveActionProps",
			"objdata": {
				"Zombies": [ {
						"Row": "5",
						"Type": "RTID(seagull@ZombieTypes)"
					}, {
						"Type": "RTID(seagull@ZombieTypes)"
					} ]
			}
		}, {
			"aliases": [ "Wave8" ],
			"objclass": "SpawnZombiesJitteredWaveActionProps",
			"objdata": {
				"AdditionalPlantfood": 1,
				"Zombies": [ {
						"Row": "1",
						"Type": "RTID(west_bull@ZombieTypes)"
					}, {
						"Row": "4",
						"Type": "RTID(lostcity_jane@ZombieTypes)"
					}, {
						"Row": "5",
						"Type": "RTID(west_bull@ZombieTypes)"
					} ]
			}
		}, {
			"aliases": [ "Wave9" ],
			"objclass": "SpawnZombiesJitteredWaveActionProps",
			"objdata": {
				"AdditionalPlantfood": 1,
				"Zombies": [ {
						"Row": "3",
						"Type": "RTID(seagull@ZombieTypes)"
					}, {
						"Row": "3",
						"Type": "RTID(modern_balloon@ZombieTypes)"
					}, {
						"Row": "2",
						"Type": "RTID(modern_balloon@ZombieTypes)"
					}, {
						"Row": "4",
						"Type": "RTID(modern_balloon@ZombieTypes)"
					}, {
						"Type": "RTID(lostcity_jane@ZombieTypes)"
					}, {
						"Type": "RTID(lostcity_jane@ZombieTypes)"
					} ]
			}
		}, {
			"aliases": [ "LevelEscalationModule" ],
			"objclass": "LevelEscalationModuleProperties",
			"objdata": {
				"FlagCount": 1,
				"PlantfoodToSpawnCount": 0,
				"PointIncrementPerWave": 20,
				"StartingPoints": 0,
				"WaveManagerProps": "RTID(WaveManagerProps@CurrentLevel)",
				"WavesPerFlag": 9,
				"ZombiePool": [ "RTID(tutorial_armor1@ZombieTypes)", "RTID(tutorial@ZombieTypes)", "RTID(tutorial_imp@ZombieTypes)" ]
			}
		}, {
			"aliases": [ "Gravestones" ],
			"objclass": "GravestoneProperties",
			"objdata": {}
		}, {
			"aliases": [ "NewWaves" ],
			"objclass": "WaveManagerModuleProperties",
			"objdata": {}
		}, {
			"aliases": [ "Wave10" ],
			"objclass": "SpawnZombiesJitteredWaveActionProps",
			"objdata": {
				"AdditionalPlantfood": 1,
				"Zombies": [ {
						"Row": "2",
						"Type": "RTID(seagull@ZombieTypes)"
					}, {
						"Row": "2",
						"Type": "RTID(lostcity_bug_armor2@ZombieTypes)"
					}, {
						"Row": "3",
						"Type": "RTID(seagull@ZombieTypes)"
					}, {
						"Row": "3",
						"Type": "RTID(lostcity_bug_armor2@ZombieTypes)"
					}, {
						"Row": "4",
						"Type": "RTID(lostcity_bug_armor2@ZombieTypes)"
					}, {
						"Row": "5",
						"Type": "RTID(lostcity_bug_armor2@ZombieTypes)"
					}, {
						"Type": "RTID(lostcity_bug_armor2@ZombieTypes)"
					} ]
			}
		}, {
			"aliases": [ "Wave11" ],
			"objclass": "SpawnZombiesJitteredWaveActionProps",
			"objdata": {
				"Zombies": [ {
						"Row": "1",
						"Type": "RTID(modern_balloon@ZombieTypes)"
					}, {
						"Row": "2",
						"Type": "RTID(lostcity_excavator@ZombieTypes)"
					}, {
						"Row": "3",
						"Type": "RTID(lostcity_jane@ZombieTypes)"
					}, {
						"Row": "4",
						"Type": "RTID(lostcity_excavator@ZombieTypes)"
					}, {
						"Row": "5",
						"Type": "RTID(modern_balloon@ZombieTypes)"
					} ]
			}
		}, {
			"aliases": [ "Wave12" ],
			"objclass": "SpawnZombiesJitteredWaveActionProps",
			"objdata": {
				"Zombies": [ {
						"Type": "RTID(eighties_gargantuar@ZombieTypes)"
					} ]
			}
		}, {
			"aliases": [ "Wave12StormEvent0" ],
			"objclass": "StormZombieSpawnerProps",
			"objdata": {
				"ColumnEnd": 7,
				"ColumnStart": 5,
				"GroupSize": 2,
				"TimeBetweenGroups": 1,
				"Type": "sandstorm",
				"Zombies": [ {
						"Type": "RTID(lostcity_bug@ZombieTypes)"
					}, {
						"Type": "RTID(modern_balloon@ZombieTypes)"
					}, {
						"Type": "RTID(seagull@ZombieTypes)"
					}, {
						"Type": "RTID(lostcity_bug_armor2@ZombieTypes)"
					}, {
						"Type": "RTID(lostcity_jane@ZombieTypes)"
					}, {
						"Type": "RTID(seagull@ZombieTypes)"
					}, {
						"Type": "RTID(lostcity_bug_armor2@ZombieTypes)"
					}, {
						"Type": "RTID(modern_balloon@ZombieTypes)"
					} ]
			}
		} ],
	"version": 1
}